DESCRIPTION.rst
MANIFEST.in
setup.cfg
setup.py
closeness/__init__.py
closeness/closeness_aggregation.py
closeness/closeness_dict.py
closeness/constants.py
closeness/fuzzy_mode.py
closeness/fuzzy_mode_dict.py
closeness/simple_mode.py
closeness/simple_mode_dict.py
closeness.egg-info/PKG-INFO
closeness.egg-info/SOURCES.txt
closeness.egg-info/dependency_links.txt
closeness.egg-info/top_level.txt