Metadata-Version: 1.1
Name: closeness
Version: 2.0.0
Summary: Mongodb documentand python dict similarity
Home-page: https://github.com/suyati/mongodb-doc-closeness
Author: Suyati Technologies
Author-email: tkannippoyil@suyati.com
License: MIT
Keywords: mongodb setuptools development relationship query
Platform: UNKNOWN
Classifier: Development Status :: 3 - Alpha
Classifier: Intended Audience :: Developers
Classifier: Topic :: Software Development :: Build Tools
Classifier: License :: OSI Approved :: MIT License
Classifier: Programming Language :: Python :: 2.6
Classifier: Programming Language :: Python :: 2.7
Classifier: Programming Language :: Python :: 3
Classifier: Programming Language :: Python :: 3.2
Classifier: Programming Language :: Python :: 3.3
Classifier: Programming Language :: Python :: 3.4
